{
  "@0x5e@homebridge-tuya-platform-1.7.0-beta.54": 8861,
  "@balansse@homebridge-vivint-1.9.0": 254,
  "@busse@homebridge-pluggit-1.2.13": 16,
  "@chazepps@homebridge-hejhome-1.1.0": 6,
  "@chazepps@homebridge-hejhome-1.1.1": 4,
  "@danielgindi@homebridge-bcp-charger-1.0.7": 3,
  "@hansfriedrich@homebridge-feller-wiser-1.0.25": 37,
  "@hernas@homebridge-panasonic-heat-pump-2.0.2": 4,
  "@hernas@homebridge-panasonic-heat-pump-2.0.3": 38,
  "@hernas@homebridge-salus-sq610-2.0.0": 5,
  "@hernas@homebridge-salus-sq610-2.0.1": 11,
  "@homebridge-plugins@homebridge-air-1.0.0-beta.0": 0,
  "@homebridge-plugins@homebridge-august-2.2.8-beta.0": 11,
  "@homebridge-plugins@homebridge-cloudflared-tunnel-1.1.1-beta.0": 5,
  "@homebridge-plugins@homebridge-ewelink-12.3.3": 313,
  "@homebridge-plugins@homebridge-govee-10.12.1": 934,
  "@homebridge-plugins@homebridge-meater-1.1.3-beta.0": 1,
  "@homebridge-plugins@homebridge-meater-1.1.4": 4,
  "@homebridge-plugins@homebridge-meross-10.8.0": 195,
  "@homebridge-plugins@homebridge-noip-3.0.5-beta.0": 0,
  "@homebridge-plugins@homebridge-rainbird-2.2.0-beta.0": 1,
  "@homebridge-plugins@homebridge-resideo-2.1.7-beta.0": 7,
  "@homebridge-plugins@homebridge-smarthq-0.1.0": 51,
  "@jdes@homebridge-tost-corp-somfy-rts-web-2.2.0": 40,
  "@milo526@homebridge-tuya-web-1.1.5": 3754,
  "@o-lukas@homebridge-smartthings-tv-2.3.6": 971,
  "@o-lukas@homebridge-smartthings-tv-2.3.7": 1600,
  "@ohmantics@homebridge-airmega-3.4.1": 52,
  "@oznu@homebridge-esp8266-garage-door-0.0.5": 2,
  "@pietrolubini@homebridge-ecoflow-1.2.1": 1,
  "@pietrolubini@homebridge-ecoflow-1.3.0": 89,
  "@puchupala@homebridge-nature-remo-multi-toggle-light-1.0.0": 24,
  "@rsauget@homebridge-flexom-3.1.0": 4,
  "@string-bean@homebridge-drayton-wiser-0.5.0": 56,
  "@switchbot@homebridge-switchbot-4.1.3": 1227,
  "@switchbot@homebridge-switchbot-4.1.4": 1020,
  "@ubreu@homebridge-helios-kwl-0.1.3": 13,
  "@ubreu@homebridge-ibricks-0.1.0": 4,
  "@vandubois@homebridge-virtual-switch-1.2.1": 1,
  "@vandubois@homebridge-virtual-switch-1.2.2": 61,
  "@xenuiswatching@homebridge-hubspace-2.1.2": 292,
  "download-statistics.json": 0,
  "homebridge-1.8.4": 2,
  "homebridge-1.8.5": 3,
  "homebridge-2-enet-1.0.1": 28,
  "homebridge-3em-energy-meter-1.1.3": 263,
  "homebridge-433-arduino-0.12.3": 24,
  "homebridge-abode-lights-2.0.1": 5,
  "homebridge-abode-lights-2.0.2": 22,
  "homebridge-actron-neo-0.1.7": 3,
  "homebridge-actron-neo-0.1.9": 25,
  "homebridge-actron-que-1.5.0": 3,
  "homebridge-adguardhome-1.7.2": 203,
  "homebridge-adt-pulse-3.4.3": 138,
  "homebridge-adt-pulse-3.4.4": 65,
  "homebridge-advanced-timer-1.1.1": 74,
  "homebridge-aeg-robot-2.2.3": 8,
  "homebridge-aeg-robot-2.2.4": 22,
  "homebridge-aeg-wellbeing-1.1.9": 21,
  "homebridge-agile-octopus-rates-1.2.10": 9,
  "homebridge-agile-octopus-rates-1.2.9": 65,
  "homebridge-air-0.2.0": 3,
  "homebridge-air-1.0.0": 2,
  "homebridge-air-q-1.1.2": 11,
  "homebridge-airconditioner-mitsubishi-au-nz-1.2.6": 32,
  "homebridge-airport-express-connected-1.4.0": 128,
  "homebridge-airport-express-connected-1.4.1": 56,
  "homebridge-airthings-1.3.1": 250,
  "homebridge-airthings-1.4.0": 394,
  "homebridge-airtouch5-platform-1.8.1": 41,
  "homebridge-airzone-cloud-0.5.2": 48,
  "homebridge-aladdin-connect-garage-door-1.0.6": 19,
  "homebridge-aladdinconnect-1.1.0": 13,
  "homebridge-alexa-0.7.0": 654,
  "homebridge-alexa-0.7.1": 2100,
  "homebridge-alexa-player-0.5.3": 337,
  "homebridge-alexa-smarthome-2.2.0": 53,
  "homebridge-alexa-smarthome-2.2.1": 2883,
  "homebridge-alphaess-2.127.0": 5,
  "homebridge-alphaess-2.128.0": 24,
  "homebridge-amazondash-mac-3.3.1": 27,
  "homebridge-ambiback-0.9.0": 8,
  "homebridge-ambient-weather-sensors-1.2.2": 66,
  "homebridge-androidtv-2.2.1": 365,
  "homebridge-anthemreceiver-0.8.2": 18,
  "homebridge-apc-back-ups-hs500-3.0.2": 4,
  "homebridge-appletv-enhanced-1.10.1": 694,
  "homebridge-appletv-enhanced-1.9.1": 1698,
  "homebridge-aqicn-1.2.1": 14,
  "homebridge-argo-1.7.1": 1,
  "homebridge-argo-1.7.2": 0,
  "homebridge-atomberg-fan-1.0.0": 15,
  "homebridge-august-2.2.8": 40,
  "homebridge-august-2.2.9": 343,
  "homebridge-automower-1.4.4": 41,
  "homebridge-automower-platform-2.2.0": 128,
  "homebridge-awair2-5.12.4": 115,
  "homebridge-awair2-5.12.5": 52,
  "homebridge-away-mode-1.6.5": 89,
  "homebridge-aws-iot-0.1.18": 41,
  "homebridge-balboa-spa-2.2.6": 21,
  "homebridge-batterytender-1.0.2": 2,
  "homebridge-bed-control-1.3.8": 58,
  "homebridge-beoplay-2.1.2": 25,
  "homebridge-better-roku-1.0.13": 208,
  "homebridge-blauberg-vento-0.8.0": 22,
  "homebridge-blauberg-vento-0.9.0": 13,
  "homebridge-ble-thermobeacon-0.0.16": 13,
  "homebridge-blinds-2.0.1": 31,
  "homebridge-blinds-cmd-3.1.0": 35,
  "homebridge-blink-for-home-3.9.2": 1084,
  "homebridge-blueair-purifier-1.0.11": 101,
  "homebridge-blueair-purifier-1.0.12": 231,
  "homebridge-bold-2.1.6": 8,
  "homebridge-bold-2.2.0": 91,
  "homebridge-bold-ble-1.2.0": 14,
  "homebridge-bold-ble-1.2.2": 23,
  "homebridge-bond-3.2.11-beta.2": 260,
  "homebridge-bond-3.2.11": 1085,
  "homebridge-boschcontrolpanel_bgseries-0.8.2": 31,
  "homebridge-boschcontrolpanel_bgseries-0.8.3": 36,
  "homebridge-bravia-2.4.9": 402,
  "homebridge-bravia-tvos-5.0.8": 371,
  "homebridge-brewer-2.1.1": 13,
  "homebridge-broadlink-heater-cooler-2.2.3": 116,
  "homebridge-broadlink-rm-pro-4.4.18": 790,
  "homebridge-broadlink-rm-pro-4.4.19": 2365,
  "homebridge-browsercam-1.2.3": 45,
  "homebridge-button-platform-1.5.1": 95,
  "homebridge-caddx-interlogix-1.3.1": 14,
  "homebridge-calendar-scheduler-2.2.2": 156,
  "homebridge-camera-ffmpeg-3.1.4": 3314,
  "homebridge-camera-ui-5.0.27": 3757,
  "homebridge-carrier-infinity-1.6.13": 152,
  "homebridge-cgd-garage-door-1.8.0": 15,
  "homebridge-cleanmate-1.4.0": 5,
  "homebridge-cloudflared-tunnel-1.1.1": 6,
  "homebridge-cloudflared-tunnel-1.1.2": 30,
  "homebridge-cmd4-advantageair-3.11.0": 76,
  "homebridge-comed-hourlypricing-1.0.1": 0,
  "homebridge-comed-hourlypricing-1.1.0": 1,
  "homebridge-comelit-platform-2.6.12": 7,
  "homebridge-comelit-sb-platform-2.3.6": 2,
  "homebridge-comelit-vedo-platform-1.2.1": 13,
  "homebridge-connectlife-ac-1.3.3": 67,
  "homebridge-cool-automation-1.0.3": 11,
  "homebridge-cool-automation-2.0.3": 48,
  "homebridge-coviva-hager-0.1.41": 13,
  "homebridge-cron-scheduler-1.3.1": 97,
  "homebridge-cuby-1.0.15": 6,
  "homebridge-daelim-smarthome-1.4.3": 6,
  "homebridge-daelim-smarthome-1.4.4": 18,
  "homebridge-dafang-mqtt-republish-2.3.1": 10,
  "homebridge-dahua-alerts-1.3.0": 167,
  "homebridge-daikin-cloud-2.6.0-beta.5": 366,
  "homebridge-daikin-cloud-2.7.0-beta.5": 337,
  "homebridge-daikin-esp8266-3.2.0": 4,
  "homebridge-daikin-local-1.1.10": 407,
  "homebridge-daikin-local-1.1.11": 266,
  "homebridge-daikin-local-platform-1.1.0": 18,
  "homebridge-daikin-local-platform-1.1.1": 171,
  "homebridge-daikin-oneplus-3.2.0": 14,
  "homebridge-daikin-oneplus-3.2.1": 197,
  "homebridge-daikin-smart-ac-1.0.0": 73,
  "homebridge-daikin-tempsensor-nocloud-1.0.8": 22,
  "homebridge-daikin-tempsensor-nocloud-1.0.9": 13,
  "homebridge-davis-1.0.0": 4,
  "homebridge-davis-1.0.1": 42,
  "homebridge-deconz-1.0.21": 1098,
  "homebridge-deconz-1.0.22": 1036,
  "homebridge-deebot-6.1.1": 546,
  "homebridge-deebotecovacs-1.4.8": 126,
  "homebridge-delay-switch-3.2.5": 728,
  "homebridge-denon-heos-2.9.7": 206,
  "homebridge-denon-tv-5.1.26": 432,
  "homebridge-denon-tv-5.1.27": 93,
  "homebridge-device-alive-1.0.5": 69,
  "homebridge-deye-1.0.2": 24,
  "homebridge-dolphin-0.5.5": 12,
  "homebridge-doorbird-1.0.1": 115,
  "homebridge-dreamscreen-rm-1.0.11": 16,
  "homebridge-dreo-4.0.3": 116,
  "homebridge-dreo-4.0.4": 394,
  "homebridge-dummy-0.9.0": 3190,
  "homebridge-dune-hd-1.3.1": 10,
  "homebridge-dynamicapi-1.0.24": 2,
  "homebridge-dyson-bp01-1.11.3": 65,
  "homebridge-dyson-pure-cool-2.8.1": 1218,
  "homebridge-dyson-pure-cool-2.8.2": 1508,
  "homebridge-easee-1.2.4": 43,
  "homebridge-ecoforest-thermostat-1.1.6": 5,
  "homebridge-ecoplug-0.6.0": 25,
  "homebridge-ecowitt-weather-sensors-2.5.0": 51,
  "homebridge-ecowitt-weather-sensors-2.5.1": 54,
  "homebridge-edomoticz-2.1.49": 279,
  "homebridge-eggtimer-plugin-1.0.33": 8,
  "homebridge-eggtimer-plugin-1.0.34": 83,
  "homebridge-egreat-androidtv-1.2.0": 12,
  "homebridge-electra-smart-2.0.1": 58,
  "homebridge-elkm1-3.0.7": 15,
  "homebridge-eltako-minisafe2-2.4.6": 8,
  "homebridge-enphase-envoy-9.5.0": 1,
  "homebridge-enphase-envoy-9.5.1": 72,
  "homebridge-enviroindoor-1.1.0": 2,
  "homebridge-enviroindoor-1.1.1": 4,
  "homebridge-enviroplus-2.2.1": 2,
  "homebridge-enviroplus-2.2.2": 8,
  "homebridge-envirourban-1.1.0": 3,
  "homebridge-envirourban-1.1.1": 4,
  "homebridge-envisalink-1.2.10": 83,
  "homebridge-envisalink-ademco-2.0.14": 17,
  "homebridge-envisalink-ademco-2.0.15": 136,
  "homebridge-eosstb-2.3.4": 19,
  "homebridge-eosstb-2.3.5": 41,
  "homebridge-esp8266-fan-1.0.0": 3,
  "homebridge-eufy-security-4.2.2": 2302,
  "homebridge-eufy-security-4.3.0": 5073,
  "homebridge-evohome-0.11.0": 101,
  "homebridge-ewelink-12.3.1": 1578,
  "homebridge-ewelink-12.3.3": 3431,
  "homebridge-exivo-1.1.3": 2,
  "homebridge-ezviz-1.0.2": 440,
  "homebridge-fenix-tft-wifi-2.1.5": 4,
  "homebridge-fhem-0.5.38": 202,
  "homebridge-fhem-0.5.42": 158,
  "homebridge-fibaro-hc3-1.1.14": 56,
  "homebridge-fibaro-home-center-3.1.1": 76,
  "homebridge-fibaro-home-center-3.2.0": 258,
  "homebridge-flair-1.3.5": 26,
  "homebridge-flobymoen-1.0.17": 209,
  "homebridge-flobymoen-1.0.18": 73,
  "homebridge-flume-3.0.3": 80,
  "homebridge-fordpass-2.0.0": 94,
  "homebridge-foxess-1.0.23": 2,
  "homebridge-foxess-1.0.24": 21,
  "homebridge-freeathome-local-api-1.13.0": 75,
  "homebridge-freeathome-local-api-1.13.1": 24,
  "homebridge-freebox-player-delta-1.3.0": 21,
  "homebridge-frigidaire-dehumidifier-2.0.0": 14,
  "homebridge-fritz-platform-6.0.19": 1582,
  "homebridge-ftp-motion-2.1.1": 17,
  "homebridge-fujitsu-airstage-2.1.0": 21,
  "homebridge-fujitsu-airstage-2.2.0": 21,
  "homebridge-futurehome-0.3.0": 8,
  "homebridge-futurehome-0.4.1": 6,
  "homebridge-genie-aladdin-connect-4.1.0": 370,
  "homebridge-glances-1.0.5": 27,
  "homebridge-gogogate2-1.1.5": 10,
  "homebridge-google-nest-sdm-1.1.23": 2093,
  "homebridge-govee-10.11.0": 360,
  "homebridge-govee-10.12.1": 6571,
  "homebridge-gpio-doorbell-2.1.1": 18,
  "homebridge-gpio-rgb-ledstrip-0.1.2": 4,
  "homebridge-gpio-rgbw-ledstrip-1.3.5": 9,
  "homebridge-gree-ac-2.1.3": 139,
  "homebridge-gree-ac-2.1.5": 280,
  "homebridge-green-mountain-grills-1.1.2": 8,
  "homebridge-grohe-sense-1.5.2": 15,
  "homebridge-gsh-3.0.1": 264,
  "homebridge-gsh-3.1.0": 978,
  "homebridge-haieracbridge-platform-1.1.2": 29,
  "homebridge-harmony-1.6.3": 753,
  "homebridge-hatch-baby-rest-5.0.1": 236,
  "homebridge-hikconnect-1.3.1": 391,
  "homebridge-hilo-2.0.0": 11,
  "homebridge-hilo-2.0.1": 86,
  "homebridge-homeconnect-1.0.7": 661,
  "homebridge-homeconnect-1.1.0": 1398,
  "homebridge-homekit-control-0.2.6": 11,
  "homebridge-homekit-control-0.2.7": 276,
  "homebridge-homeqtt-alarm-3.1.1": 11,
  "homebridge-homewizard-energy-socket-1.5.1": 55,
  "homebridge-homewizard-power-consumption-1.6.3": 84,
  "homebridge-homeworks-0.7.0": 4,
  "homebridge-hsd-1.1.10": 78,
  "homebridge-http-curtain-1.5.0": 11,
  "homebridge-http-garage-doors-0.1.2": 54,
  "homebridge-http-iot-1.2.0": 27,
  "homebridge-http-iot-1.3.1": 10,
  "homebridge-http-json-thermometer-1.1.2": 33,
  "homebridge-http-leak-sensor-1.0.2": 5,
  "homebridge-http-sensors-switches-1.1.5": 59,
  "homebridge-http-sensors-switches-1.1.6": 100,
  "homebridge-http-switch-0.5.36": 260,
  "homebridge-hubitat-tonesto7-2.10.0-beta.7": 43,
  "homebridge-hubitat-tonesto7-2.9.4": 82,
  "homebridge-hubspace-1.3.0": 148,
  "homebridge-hue-0.14.6": 1512,
  "homebridge-hue-0.14.7": 1255,
  "homebridge-hunter-hydrawise-1.1.2": 109,
  "homebridge-hyperion-jub-1.0.12": 55,
  "homebridge-hyundai-bluelink-1.4.1": 45,
  "homebridge-i6-bigassfans-0.6.0": 171,
  "homebridge-infinitude-v2-0.9.5": 2,
  "homebridge-intelliclima-1.0.1": 6,
  "homebridge-intelliclima-1.0.2": 2,
  "homebridge-intercom-automation-hat-1.1.0": 10,
  "homebridge-irobot-2.1.16": 339,
  "homebridge-irobot-v2-3.2.3": 707,
  "homebridge-irobot-v2-3.2.4": 107,
  "homebridge-itho-daalderop-1.1.6": 19,
  "homebridge-jablotron-3.0.0": 35,
  "homebridge-jewish-calendar-1.1.1": 14,
  "homebridge-juicebox-1.0.0": 9,
  "homebridge-kasa-hub-0.8.1": 139,
  "homebridge-kasa-hub-0.9.0": 867,
  "homebridge-kasa-python-2.5.16": 30,
  "homebridge-kasa-python-2.6.1": 79,
  "homebridge-keylights-1.2.4": 316,
  "homebridge-kiwigrid-1.2.3": 8,
  "homebridge-kodi-1.0.1": 77,
  "homebridge-konnected-1.3.2": 94,
  "homebridge-kumo-1.10.7": 56,
  "homebridge-landroid-0.12.3": 239,
  "homebridge-lay-z-spa-1.2.0": 20,
  "homebridge-level-sense-1.3.2": 6,
  "homebridge-leviton-2.0.1": 171,
  "homebridge-levoit-air-purifier-3.0.1": 706,
  "homebridge-levoit-humidifiers-1.14.1": 303,
  "homebridge-lg-enervu-0.1.3": 12,
  "homebridge-lg-thinq-1.8.9": 2701,
  "homebridge-lg-thinq-ac-2.2.0": 176,
  "homebridge-lgwebos-tv-3.2.8": 232,
  "homebridge-lgwebos-tv-3.3.0": 560,
  "homebridge-lifx-plugin-0.3.0": 302,
  "homebridge-lighthouse-1.1.4": 5,
  "homebridge-lightwaverf-0.4.3": 24,
  "homebridge-linak-1.1.2": 17,
  "homebridge-litter-robot-connect-1.2.0": 64,
  "homebridge-logic-switch-1.0.0": 17,
  "homebridge-logo-platform-1.4.4": 20,
  "homebridge-logo-platform-1.4.5": 36,
  "homebridge-loxone-control-1.3.1": 32,
  "homebridge-loxone-proxy-1.10.0": 119,
  "homebridge-lutron-caseta-leap-2.6.0": 654,
  "homebridge-luxtronik2-1.2.4": 17,
  "homebridge-luxtronik2-1.2.5": 10,
  "homebridge-magic-occupancy-4.0.0": 20,
  "homebridge-magic-occupancy-4.0.1": 430,
  "homebridge-magichome-dynamic-platform-1.9.11": 439,
  "homebridge-meater-1.1.3": 7,
  "homebridge-meater-1.1.4": 29,
  "homebridge-melcloud-control-3.3.30": 283,
  "homebridge-melcloud-control-3.3.31": 38,
  "homebridge-meraki-control-1.1.34": 10,
  "homebridge-meraki-control-1.1.35": 1,
  "homebridge-mercedesme-2.1.2": 44,
  "homebridge-meross-10.7.0": 1360,
  "homebridge-meross-10.8.0": 3370,
  "homebridge-mertik-fireplace-1.4.0": 4,
  "homebridge-messenger-0.0.8": 313,
  "homebridge-mhacwifi1-lan-0.4.1": 49,
  "homebridge-mhi-wfrac-1.0.1": 0,
  "homebridge-mhi-wfrac-1.0.2": 24,
  "homebridge-mi-humidifier-2.4.6": 154,
  "homebridge-mi-hygrothermograph-3.4.2": 402,
  "homebridge-micronova-agua-iot-stove-1.1.0": 12,
  "homebridge-midea-platform-1.2.1": 91,
  "homebridge-midea-platform-1.2.2": 826,
  "homebridge-mieleathome-3.5.0": 244,
  "homebridge-mihomegateway-2.4.0": 90,
  "homebridge-milighthub-platform-1.0.1": 16,
  "homebridge-miot-1.7.4": 4257,
  "homebridge-miot-1.7.5": 1072,
  "homebridge-mobilelink-2.1.0": 38,
  "homebridge-moodo-2.1.3": 14,
  "homebridge-moonraker-1.0.2": 33,
  "homebridge-mqtt-1.0.1": 129,
  "homebridge-mqtt-ceiling-fan-remote-1.0.6": 25,
  "homebridge-mqtt-tasmota-0.12.0": 204,
  "homebridge-mqttsmokesensor-1.2.2": 2,
  "homebridge-mqttsmokesensor-1.2.3": 21,
  "homebridge-mqttthing-1.1.47": 1412,
  "homebridge-multiswitcheroo-3.0.4": 93,
  "homebridge-musiccast-multiroom-0.2.10": 97,
  "homebridge-musiccast-multiroom-0.2.11": 60,
  "homebridge-my-wallbox-1.1.22": 7,
  "homebridge-my-wallbox-1.1.23": 71,
  "homebridge-mylink-2.0.5": 59,
  "homebridge-myplace-2.1.1": 0,
  "homebridge-myplace-2.1.2": 20,
  "homebridge-myq-3.4.4": 2012,
  "homebridge-mysmartblinds-bridge-3.0.1": 13,
  "homebridge-naim-audio-1.2.5": 17,
  "homebridge-nb-1.4.28": 315,
  "homebridge-nb-1.4.29": 274,
  "homebridge-neptun-smart-1.0.10": 8,
  "homebridge-ness-d16x-1.0.0": 5,
  "homebridge-nest-4.6.9": 3065,
  "homebridge-nest-cam-7.5.4": 676,
  "homebridge-network-presence-1.2.3": 311,
  "homebridge-ngbs-icon-thermostat-1.1.1": 11,
  "homebridge-node-alarm-dot-com-1.10.0": 97,
  "homebridge-node-alarm-dot-com-1.10.1": 522,
  "homebridge-noip-3.0.5": 9,
  "homebridge-noip-3.0.6": 41,
  "homebridge-nordpool-baltics-1.4.7": 23,
  "homebridge-nordpool-baltics-1.4.8": 4,
  "homebridge-notifyevents-1.3.2": 158,
  "homebridge-nukiio-0.16.1": 122,
  "homebridge-nuvo-2.2.7": 5,
  "homebridge-octoprint-motion-1.3.6": 53,
  "homebridge-omnik-1.2.1": 7,
  "homebridge-omnilink-platform-1.5.17": 3,
  "homebridge-omnilink-platform-1.5.18": 70,
  "homebridge-onstar-1.5.39": 116,
  "homebridge-open-sesame-0.5.0": 52,
  "homebridge-openrgb-1.4.3": 44,
  "homebridge-opensprinkler-api-2.0.4": 18,
  "homebridge-openwebif-tv-4.0.25": 55,
  "homebridge-openwebif-tv-4.0.26": 21,
  "homebridge-oppo-udp-5.1.0": 13,
  "homebridge-orbit-irrigation-1.2.35": 319,
  "homebridge-orbit-irrigation-1.2.36": 665,
  "homebridge-otgw-2.1.26": 6,
  "homebridge-otgw-2.1.27": 4,
  "homebridge-overda-uranus-5.1.0": 2,
  "homebridge-owfs-1.5.4": 6,
  "homebridge-owfs-1.5.5": 2,
  "homebridge-p1-1.3.24": 36,
  "homebridge-p1-1.3.25": 36,
  "homebridge-panasonic-ac-platform-5.3.0": 243,
  "homebridge-panasonic-ac-platform-5.3.1": 32,
  "homebridge-panasonic-miraie-ac-platform-1.0.10": 16,
  "homebridge-pc-volume-1.2.4": 20,
  "homebridge-pentair-intellicenter-2.1.1": 22,
  "homebridge-pentair-screenlogic-3.0.2": 54,
  "homebridge-people-pro-0.11.6": 203,
  "homebridge-petkit-pet-feeder-3.2.2": 32,
  "homebridge-petkit-platform-1.0.7": 90,
  "homebridge-petsafe-smart-feed-2.0.4": 16,
  "homebridge-philips-air-3.5.2": 188,
  "homebridge-philips-android-tv-0.10.12": 321,
  "homebridge-philipsair-platform-1.0.2": 115,
  "homebridge-philipstv-saphitvos-1.0.1": 69,
  "homebridge-pichler-pkom4-1.1.8-beta.8": 2,
  "homebridge-pichler-pkom4-1.1.9": 7,
  "homebridge-pico-1.2.2": 61,
  "homebridge-pico-w-bridge-1.0.3": 11,
  "homebridge-pihole-0.4.3": 645,
  "homebridge-platform-maxcube-2.0.15": 38,
  "homebridge-platform-orbit-1.5.3": 36,
  "homebridge-playstation-1.6.0": 104,
  "homebridge-playstation-1.6.2": 1214,
  "homebridge-playstation-game-title-1.0.7": 247,
  "homebridge-plex-webhooks-2.2.0": 208,
  "homebridge-plugin-govee-1.2.7": 349,
  "homebridge-plugin-update-check-1.0.2": 160,
  "homebridge-porsche-taycan-1.21.1": 12,
  "homebridge-presence-switch-msgraph-1.8.0": 26,
  "homebridge-presence-switch-slack-1.0.0": 5,
  "homebridge-printer-1.1.1": 229,
  "homebridge-programmable-http-switch-1.0.3": 125,
  "homebridge-prosegur-1.1.0": 4,
  "homebridge-prusa-link-2.1.0": 35,
  "homebridge-purpleair-1.0.8": 6,
  "homebridge-purpleair-sensor-3.0.2": 47,
  "homebridge-qolsys-0.5.0": 31,
  "homebridge-qolsys-0.5.1": 76,
  "homebridge-ra2-select-1.1.2": 15,
  "homebridge-rachio-irrigation-1.3.6": 269,
  "homebridge-rachio-irrigation-1.3.7": 687,
  "homebridge-rademacher-homepilot-0.11.0": 337,
  "homebridge-rademacher-homepilot-0.11.1": 182,
  "homebridge-radiora2-1.7.7": 33,
  "homebridge-rainbird-2.1.2": 312,
  "homebridge-rainbird-2.2.0": 261,
  "homebridge-ratgdo-2.5.0": 266,
  "homebridge-ratgdo-2.6.0": 103,
  "homebridge-red-alert-via-kumta-2.5.0": 21,
  "homebridge-red-alert-via-kumta-2.5.1": 26,
  "homebridge-remootio-1.4.0-beta.2": 2,
  "homebridge-remootio-1.4.0": 54,
  "homebridge-resideo-2.1.7": 8,
  "homebridge-resideo-2.1.8": 158,
  "homebridge-rgb-ledstrip-1.0.1": 19,
  "homebridge-ring-13.1.0": 9541,
  "homebridge-ring-13.2.0": 3819,
  "homebridge-rinnai-controlr-1.0.26": 27,
  "homebridge-rinnai-touch-platform-3.4.12": 2,
  "homebridge-rinnai-touch-platform-3.4.13": 41,
  "homebridge-robonect-1.1.17": 9,
  "homebridge-robonect-1.1.18": 54,
  "homebridge-rointe-unofficial-4.0.1": 6,
  "homebridge-roomba2-1.4.0": 519,
  "homebridge-roomme-1.0.16": 4,
  "homebridge-rpi-1.8.23": 466,
  "homebridge-rpi-1.8.24": 432,
  "homebridge-rpi-rf-switch-2.2.3": 19,
  "homebridge-samsung-tizen-5.2.7": 1920,
  "homebridge-samsungtv-2014-1.2.5": 140,
  "homebridge-samsungtvht-1.0.14": 243,
  "homebridge-saphi-tv-1.0.3": 47,
  "homebridge-sc-1.1.5": 10,
  "homebridge-schedule-1.0.136": 89,
  "homebridge-scout-1.5.3": 2,
  "homebridge-securitysystem-8.4.1": 138,
  "homebridge-securitysystem-9.0.0": 340,
  "homebridge-sensibo-ac-2.5.1": 503,
  "homebridge-sensit-tank-monitor-1.4.0": 5,
  "homebridge-sepsadsecurity-0.2.1": 6,
  "homebridge-sharkiq-1.3.1": 269,
  "homebridge-sharkiq-1.3.2": 244,
  "homebridge-shelly-0.19.1": 1022,
  "homebridge-shelly-ng-1.6.0": 2317,
  "homebridge-shortcuts-buttons-3.5.2": 6,
  "homebridge-shortcuts-buttons-3.5.3": 326,
  "homebridge-sht3x-2.1.1": 2,
  "homebridge-signalk-1.6.0": 156,
  "homebridge-simplisafe3-1.10.13": 431,
  "homebridge-sinricpro-1.1.2": 82,
  "homebridge-sinricpro-1.1.4": 81,
  "homebridge-skybell-2.1.5": 3,
  "homebridge-slide-shutter-1.0.6": 9,
  "homebridge-sma-home-manager-1.1.8": 106,
  "homebridge-smart-irrigation-1.7.2": 56,
  "homebridge-smartcielo-0.0.8": 14,
  "homebridge-smartdry-1.0.9": 2,
  "homebridge-smartglass-1.0.4": 47,
  "homebridge-smarthomeng-2.0.7": 9,
  "homebridge-smartthings-2.3.8": 719,
  "homebridge-smartthings-ik-1.5.21": 1873,
  "homebridge-smtp-motion-1.2.1": 25,
  "homebridge-snowsense-2.0.5": 16,
  "homebridge-solaxcloud-api-2.3.3": 36,
  "homebridge-solis5g-battery-1.1.10": 7,
  "homebridge-somfy-hotwired-1.3.0": 27,
  "homebridge-somfy-tahoma-screen-1.1.1": 3,
  "homebridge-somfy-tahoma-screen-1.1.2": 237,
  "homebridge-somneo-1.6.1": 14,
  "homebridge-sonos-0.4.0": 288,
  "homebridge-sonos-multiroom-0.6.0": 49,
  "homebridge-sonos-starter-track-1.0.19": 77,
  "homebridge-sony-audio-1.2.0": 70,
  "homebridge-sp108e-platform-1.1.3": 6,
  "homebridge-spanet-2.1.1": 8,
  "homebridge-spotify-speaker-1.3.3": 87,
  "homebridge-spruce-irrigation-1.1.1": 2,
  "homebridge-stagekit-1.2.4": 2,
  "homebridge-stagg-ekg-plus-1.0.21": 6,
  "homebridge-star-projector-1.0.6": 82,
  "homebridge-sunsa-1.1.1": 25,
  "homebridge-switch-button-1.0.3": 113,
  "homebridge-switchbot-bluetooth-platform-1.2.6": 219,
  "homebridge-switchbot-for-mac-0.2.1": 40,
  "homebridge-switchbot-sensor-ble-1.4.0": 82,
  "homebridge-switcher-platform-4.4.7": 201,
  "homebridge-tadiran-ac-1.1.0": 70,
  "homebridge-tado-ac-4.1.2": 279,
  "homebridge-tado-platform-6.0.14": 402,
  "homebridge-tapo-camera-2.4.9": 1473,
  "homebridge-tapo-camera-2.5.1": 2255,
  "homebridge-tasmota-0.1.18": 227,
  "homebridge-tasmota-control-1.0.5": 164,
  "homebridge-tasmota-control-1.0.6": 32,
  "homebridge-tasmota-zbbridge-1.10.0": 86,
  "homebridge-tasmota-zbbridge-1.9.1": 87,
  "homebridge-tcc-0.2.34": 279,
  "homebridge-television-universal-control-1.2.0": 14,
  "homebridge-temperature-sensor-dht-1.0.4": 68,
  "homebridge-tempstick-1.0.6": 2,
  "homebridge-tesla-4.3.5": 398,
  "homebridge-tesy-heater-v2-4.0.45": 7,
  "homebridge-texecom-connect-0.0.10": 16,
  "homebridge-texecom-connect-0.0.11": 15,
  "homebridge-thermobit-3.0.0": 2,
  "homebridge-tibber-price-1.1.0": 61,
  "homebridge-tibberswitch-0.3.6": 35,
  "homebridge-tidbyt-0.7.1": 23,
  "homebridge-tiko-1.1.2": 10,
  "homebridge-tivo-control-1.2.3": 10,
  "homebridge-tovala-1.0.5": 2,
  "homebridge-tp-link-access-control-1.0.7": 169,
  "homebridge-tp-link-tapo-4.1.1": 1708,
  "homebridge-tp-link-tapo-4.1.2": 2323,
  "homebridge-tplink-smarthome-8.0.3": 4207,
  "homebridge-ttlock-1.1.0": 81,
  "homebridge-tuya-3.1.1": 2564,
  "homebridge-tuya-ir-1.1.0": 216,
  "homebridge-tuya-platform-1.5.0": 444,
  "homebridge-tuya-platform-talrhvfork-1.6.0": 50,
  "homebridge-twinkly-plus-0.5.2": 143,
  "homebridge-uconnect-1.0.1": 21,
  "homebridge-ueboom-1.0.2": 33,
  "homebridge-unifi-access-1.4.0": 121,
  "homebridge-unifi-access-1.5.0": 290,
  "homebridge-unifi-occupancy-1.3.0": 114,
  "homebridge-unifi-poe-control-1.3.0": 9,
  "homebridge-unifi-poe-control-1.3.1": 145,
  "homebridge-unifi-protect-7.8.0": 2222,
  "homebridge-unifi-protect-7.8.2": 6502,
  "homebridge-unifi-protect-camera-motion-0.6.4-beta-002": 81,
  "homebridge-unifi-smartpower-2.1.3": 6,
  "homebridge-unifi-smartpower-2.2.0": 128,
  "homebridge-ups-1.2.13": 189,
  "homebridge-ups-1.2.14": 166,
  "homebridge-velux-active-1.0.0": 62,
  "homebridge-verisure-2.0.1": 103,
  "homebridge-vesync-v2-2.4.1": 253,
  "homebridge-videodoorbell-0.3.2": 53,
  "homebridge-vieramatic-4.0.51": 138,
  "homebridge-volvo-1.0.6": 48,
  "homebridge-washingmachine-pow-2.1.3": 16,
  "homebridge-wattbox-3.0.1": 2,
  "homebridge-wattbox-3.1.0": 10,
  "homebridge-wattbox-ip-1.1.0": 3,
  "homebridge-wattbox-ip-1.1.1": 10,
  "homebridge-weather-plus-3.3.5": 1314,
  "homebridge-weatherflow-tempest-4.1.0": 102,
  "homebridge-weatherflow-tempest-4.1.1": 163,
  "homebridge-webos-tv-2.4.5": 2388,
  "homebridge-webos-tv-2.4.6": 693,
  "homebridge-website-change-check-1.0.9": 4,
  "homebridge-wemo-6.1.2": 596,
  "homebridge-winix-purifiers-2.1.0": 161,
  "homebridge-winix-purifiers-2.1.1": 270,
  "homebridge-wiser-2.1.3": 34,
  "homebridge-wled-ws-0.0.16": 535,
  "homebridge-wol-6.0.1": 1060,
  "homebridge-wol-7.0.0-beta.0": 127,
  "homebridge-ws-2.7.28": 246,
  "homebridge-ws-2.7.29": 194,
  "homebridge-wyze-robovac-1.5.1": 51,
  "homebridge-wyze-smart-home-0.5.46": 293,
  "homebridge-wyze-smart-home-0.5.47": 1769,
  "homebridge-xbox-tv-3.1.22": 282,
  "homebridge-xbox-tv-3.1.23": 54,
  "homebridge-xfinityhome-3.5.1": 33,
  "homebridge-xfinityhome-3.5.2": 0,
  "homebridge-xiaomi-aqara-ac-cooler-1.0.5": 32,
  "homebridge-xiaomi-fan-1.5.9": 340,
  "homebridge-xiaomi-mi-air-purifier-2.0.2": 421,
  "homebridge-xiaomi-roborock-vacuum-0.31.1": 78,
  "homebridge-xiaomi-roborock-vacuum-0.32.0": 2583,
  "homebridge-yamaha-receiver-0.0.7": 195,
  "homebridge-yeelighter-2.7.0": 644,
  "homebridge-yet-another-ping-0.0.5": 40,
  "homebridge-yindl-0.12.5": 13,
  "homebridge-yokis-usb-1.1.4": 4,
  "homebridge-yolink-1.6.0": 3,
  "homebridge-yolink-1.6.1": 301,
  "homebridge-z2m-1.9.3": 2231,
  "homebridge-zidoo-androidtv-3.1.0": 21,
  "homebridge-zidoo-androidtv-4.0.0": 71,
  "homebridge-zigbee-nt-2.6.1": 81,
  "homebridge-zigbee-nt-2.6.2": 1516,
  "homebridge-zp-1.4.48": 1244,
  "homebridge-zp-1.4.49": 1195
}